django_mailchimp_v1.3-1.4.0.dist-info/DESCRIPTION.rst
django_mailchimp_v1.3-1.4.0.dist-info/METADATA
django_mailchimp_v1.3-1.4.0.dist-info/RECORD
django_mailchimp_v1.3-1.4.0.dist-info/WHEEL
django_mailchimp_v1.3-1.4.0.dist-info/metadata.json
django_mailchimp_v1.3-1.4.0.dist-info/top_level.txt
mailchimp/__init__.py
mailchimp/admin.py
mailchimp/chimp.py
mailchimp/constants.py
mailchimp/exceptions.py
mailchimp/managers.py
mailchimp/models.py
mailchimp/settings.py
mailchimp/signals.py
mailchimp/urls.py
mailchimp/utils.py
mailchimp/views.py
mailchimp/chimpy/__init__.py
mailchimp/chimpy/chimpy.py
mailchimp/chimpy/test_chimpy.py
mailchimp/chimpy/utils.py
mailchimp/locale/de/LC_MESSAGES/django.mo
mailchimp/locale/de/LC_MESSAGES/django.po
mailchimp/locale/en/LC_MESSAGES/django.mo
mailchimp/locale/en/LC_MESSAGES/django.po
mailchimp/locale/fr/LC_MESSAGES/django.po
mailchimp/locale/it/LC_MESSAGES/django.po
mailchimp/management/__init__.py
mailchimp/management/commands/__init__.py
mailchimp/management/commands/mcdequeue.py
mailchimp/management/commands/mcmakemerge.py
mailchimp/management/commands/mcsitegroups.py
mailchimp/management/commands/mcwebhooks.py
mailchimp/migrations/0001_initial.py
mailchimp/migrations/0002_auto_20161017_1603.py
mailchimp/migrations/0003_auto_20161019_1645.py
mailchimp/migrations/__init__.py
mailchimp/south_migrations/0001_initial.py
mailchimp/south_migrations/0002_added_queue.py
mailchimp/south_migrations/0003_fixed_template_id.py
mailchimp/south_migrations/0004_fixed_template_id_max.py
mailchimp/south_migrations/0005_added_link_to_object.py
mailchimp/south_migrations/0006_added_locks.py
mailchimp/south_migrations/0007_extra_info.py
mailchimp/south_migrations/0008_auto__chg_field_reciever_email__chg_field_queue_from_email__chg_field_.py
mailchimp/south_migrations/__init__.py
mailchimp/templates/mailchimp/campaign_information.html
mailchimp/templates/mailchimp/overview.html
mailchimp/templates/mailchimp/send_button.html
mailchimp/templates/mailchimp/send_test.html
mailchimp/templatetags/__init__.py
mailchimp/templatetags/mailchimp_admin_tags.py
mailchimp/templatetags/mailchimp_tags.py
