Metadata-Version: 2.0
Name: django-mailchimp-v1.3
Version: 1.4.0
Summary: Mailchimp wrapper for Django, using Mailchimp API 1.3
Home-page: http://github.com/divio/django-mailchimp
Author: Jonas Obrist et al.
Author-email: UNKNOWN
License: UNKNOWN
Platform: UNKNOWN
